aitg_doctools/chunk.py
aitg_doctools/clean.py
aitg_doctools/util.py
aitg_doctools-0.2.0.dist-info/WHEEL
aitg_doctools-0.2.0.dist-info/METADATA
aitg_doctools-0.2.0.dist-info/RECORD
